pptxer/__init__.py
pptxer/__main__.py
pptxer/cli.py
pptxer/presentations_downloader.py
pptxer/presentations_text_extractor.py
pptxer/util.py
pptxer-0.1.dist-info/LICENSE
pptxer-0.1.dist-info/METADATA
pptxer-0.1.dist-info/WHEEL
pptxer-0.1.dist-info/entry_points.txt
pptxer-0.1.dist-info/top_level.txt
pptxer-0.1.dist-info/RECORD
