Metadata-Version: 2.1
Name: pptxer
Version: 0.1
Summary: A fast high-level presentations scraper for Python and command Line
Home-page: https://github.com/yazeed44/pptxer
Author: Yazeed Almuqwishi
Author-email: yazeed.almuqwishi@gmail.com
License: UNKNOWN
Project-URL: Bug Tracker, https://github.com/yazeed44/pptxer/issues
Platform: UNKNOWN
Classifier: Programming Language :: Python :: 3
Classifier: License :: OSI Approved :: MIT License
Classifier: Operating System :: OS Independent
License-File: LICENSE
Requires-Dist: fake-headers
Requires-Dist: googlesearch-python
Requires-Dist: python-pptx
Requires-Dist: requests
Requires-Dist: click
